gene_rule_parser/#main.py#
gene_rule_parser/__init__.py
gene_rule_parser/analisis.py
gene_rule_parser/gen_lexer.py
gene_rule_parser/gen_parser.py
gene_rule_parser/gene_expression_parser.py
gene_rule_parser/main.py
gene_rule_parser/parser.out
gene_rule_parser/parsetab.py
gene_rule_parser-0.1.5.dist-info/METADATA
gene_rule_parser-0.1.5.dist-info/WHEEL
gene_rule_parser-0.1.5.dist-info/entry_points.txt
gene_rule_parser-0.1.5.dist-info/RECORD
