Metadata-Version: 2.1
Name: gene-rule-parser
Version: 0.1.5
Summary: Basic language to parse genetic rules to a structure
Author: pineiden
Author-email: dpineda@uchile.cl
Requires-Python: >=3.11,<4.0
Classifier: Programming Language :: Python :: 3
Classifier: Programming Language :: Python :: 3.11
Classifier: Programming Language :: Python :: 3.12
Requires-Dist: cobra (>=0.29.0,<0.30.0)
Requires-Dist: ipython (>=8.26.0,<9.0.0)
Requires-Dist: ply (>=3.11,<4.0)
Requires-Dist: polars (>=1.7.1,<2.0.0)
Requires-Dist: pydantic (>=2.8.2,<3.0.0)
Requires-Dist: rich (>=13.7.1,<14.0.0)
Requires-Dist: typer (>=0.12.3,<0.13.0)
Requires-Dist: ujson (>=5.10.0,<6.0.0)
